{
	"textures": [
		{
			"image": "pokemons.png",
			"format": "RGBA8888",
			"size": {
				"w": 287,
				"h": 2045
			},
			"scale": 1,
			"frames": [
				{
					"filename": "pokemons",
					"rotated": false,
					"trimmed": false,
					"sourceSize": {
						"w": 243,
						"h": 2043
					},
					"spriteSourceSize": {
						"x": 0,
						"y": 0,
						"w": 243,
						"h": 2043
					},
					"frame": {
						"x": 1,
						"y": 1,
						"w": 243,
						"h": 2043
					},
					"anchor": {
						"x": 0.5,
						"y": 0.5
					}
				},
				{
					"filename": "1/portrait",
					"rotated": false,
					"trimmed": false,
					"sourceSize": {
						"w": 40,
						"h": 40
					},
					"spriteSourceSize": {
						"x": 0,
						"y": 0,
						"w": 40,
						"h": 40
					},
					"frame": {
						"x": 246,
						"y": 1,
						"w": 40,
						"h": 40
					},
					"anchor": {
						"x": 0.5,
						"y": 0.5
					}
				},
				{
					"filename": "4/portrait",
					"rotated": false,
					"trimmed": false,
					"sourceSize": {
						"w": 40,
						"h": 40
					},
					"spriteSourceSize": {
						"x": 0,
						"y": 0,
						"w": 40,
						"h": 40
					},
					"frame": {
						"x": 246,
						"y": 43,
						"w": 40,
						"h": 40
					},
					"anchor": {
						"x": 0.5,
						"y": 0.5
					}
				},
				{
					"filename": "7/portrait",
					"rotated": false,
					"trimmed": false,
					"sourceSize": {
						"w": 40,
						"h": 40
					},
					"spriteSourceSize": {
						"x": 0,
						"y": 0,
						"w": 40,
						"h": 40
					},
					"frame": {
						"x": 246,
						"y": 85,
						"w": 40,
						"h": 40
					},
					"anchor": {
						"x": 0.5,
						"y": 0.5
					}
				},
				{
					"filename": "1/0/1/0",
					"rotated": false,
					"trimmed": false,
					"sourceSize": {
						"w": 24,
						"h": 17
					},
					"spriteSourceSize": {
						"x": 0,
						"y": 0,
						"w": 24,
						"h": 17
					},
					"frame": {
						"x": 246,
						"y": 127,
						"w": 24,
						"h": 17
					},
					"anchor": {
						"x": 0.5,
						"y": 0.5
					}
				},
				{
					"filename": "4/0/4/0",
					"rotated": false,
					"trimmed": false,
					"sourceSize": {
						"w": 14,
						"h": 22
					},
					"spriteSourceSize": {
						"x": 0,
						"y": 0,
						"w": 14,
						"h": 22
					},
					"frame": {
						"x": 272,
						"y": 127,
						"w": 14,
						"h": 22
					},
					"anchor": {
						"x": 0.5,
						"y": 0.5
					}
				},
				{
					"filename": "1/0/2/1",
					"rotated": false,
					"trimmed": false,
					"sourceSize": {
						"w": 23,
						"h": 21
					},
					"spriteSourceSize": {
						"x": 0,
						"y": 0,
						"w": 23,
						"h": 21
					},
					"frame": {
						"x": 246,
						"y": 146,
						"w": 23,
						"h": 21
					},
					"anchor": {
						"x": 0.5,
						"y": 0.5
					}
				},
				{
					"filename": "4/0/4/1",
					"rotated": false,
					"trimmed": false,
					"sourceSize": {
						"w": 15,
						"h": 22
					},
					"spriteSourceSize": {
						"x": 0,
						"y": 0,
						"w": 15,
						"h": 22
					},
					"frame": {
						"x": 271,
						"y": 151,
						"w": 15,
						"h": 22
					},
					"anchor": {
						"x": 0.5,
						"y": 0.5
					}
				},
				{
					"filename": "7/0/2/1",
					"rotated": false,
					"trimmed": false,
					"sourceSize": {
						"w": 23,
						"h": 19
					},
					"spriteSourceSize": {
						"x": 0,
						"y": 0,
						"w": 23,
						"h": 19
					},
					"frame": {
						"x": 246,
						"y": 169,
						"w": 23,
						"h": 19
					},
					"anchor": {
						"x": 0.5,
						"y": 0.5
					}
				},
				{
					"filename": "7/1/2/1",
					"rotated": false,
					"trimmed": false,
					"sourceSize": {
						"w": 23,
						"h": 19
					},
					"spriteSourceSize": {
						"x": 0,
						"y": 0,
						"w": 23,
						"h": 19
					},
					"frame": {
						"x": 246,
						"y": 169,
						"w": 23,
						"h": 19
					},
					"anchor": {
						"x": 1,
						"y": 0.47368421052631576
					}
				},
				{
					"filename": "7/0/4/0",
					"rotated": false,
					"trimmed": false,
					"sourceSize": {
						"w": 15,
						"h": 19
					},
					"spriteSourceSize": {
						"x": 0,
						"y": 0,
						"w": 15,
						"h": 19
					},
					"frame": {
						"x": 271,
						"y": 175,
						"w": 15,
						"h": 19
					},
					"anchor": {
						"x": 0.5,
						"y": 0.5
					}
				},
				{
					"filename": "7/1/4/0",
					"rotated": false,
					"trimmed": false,
					"sourceSize": {
						"w": 15,
						"h": 19
					},
					"spriteSourceSize": {
						"x": 0,
						"y": 0,
						"w": 15,
						"h": 19
					},
					"frame": {
						"x": 271,
						"y": 175,
						"w": 15,
						"h": 19
					},
					"anchor": {
						"x": 0.5,
						"y": 0.5
					}
				},
				{
					"filename": "7/0/2/0",
					"rotated": false,
					"trimmed": false,
					"sourceSize": {
						"w": 23,
						"h": 18
					},
					"spriteSourceSize": {
						"x": 0,
						"y": 0,
						"w": 23,
						"h": 18
					},
					"frame": {
						"x": 246,
						"y": 190,
						"w": 23,
						"h": 18
					},
					"anchor": {
						"x": 0.5,
						"y": 0.5
					}
				},
				{
					"filename": "7/1/2/0",
					"rotated": false,
					"trimmed": false,
					"sourceSize": {
						"w": 23,
						"h": 18
					},
					"spriteSourceSize": {
						"x": 0,
						"y": 0,
						"w": 23,
						"h": 18
					},
					"frame": {
						"x": 246,
						"y": 190,
						"w": 23,
						"h": 18
					},
					"anchor": {
						"x": 0.5,
						"y": 0.5
					}
				},
				{
					"filename": "7/0/4/1",
					"rotated": false,
					"trimmed": false,
					"sourceSize": {
						"w": 15,
						"h": 19
					},
					"spriteSourceSize": {
						"x": 0,
						"y": 0,
						"w": 15,
						"h": 19
					},
					"frame": {
						"x": 271,
						"y": 196,
						"w": 15,
						"h": 19
					},
					"anchor": {
						"x": 0.5,
						"y": 0.5
					}
				},
				{
					"filename": "7/1/4/1",
					"rotated": false,
					"trimmed": false,
					"sourceSize": {
						"w": 15,
						"h": 19
					},
					"spriteSourceSize": {
						"x": 0,
						"y": 0,
						"w": 15,
						"h": 19
					},
					"frame": {
						"x": 271,
						"y": 196,
						"w": 15,
						"h": 19
					},
					"anchor": {
						"x": 0.5333333333333333,
						"y": 1
					}
				},
				{
					"filename": "7/0/2/2",
					"rotated": false,
					"trimmed": false,
					"sourceSize": {
						"w": 23,
						"h": 18
					},
					"spriteSourceSize": {
						"x": 0,
						"y": 0,
						"w": 23,
						"h": 18
					},
					"frame": {
						"x": 246,
						"y": 210,
						"w": 23,
						"h": 18
					},
					"anchor": {
						"x": 0.5,
						"y": 0.5
					}
				},
				{
					"filename": "7/1/2/2",
					"rotated": false,
					"trimmed": false,
					"sourceSize": {
						"w": 23,
						"h": 18
					},
					"spriteSourceSize": {
						"x": 0,
						"y": 0,
						"w": 23,
						"h": 18
					},
					"frame": {
						"x": 246,
						"y": 210,
						"w": 23,
						"h": 18
					},
					"anchor": {
						"x": 0.6521739130434783,
						"y": 0.5
					}
				},
				{
					"filename": "7/0/0/0",
					"rotated": false,
					"trimmed": false,
					"sourceSize": {
						"w": 15,
						"h": 18
					},
					"spriteSourceSize": {
						"x": 0,
						"y": 0,
						"w": 15,
						"h": 18
					},
					"frame": {
						"x": 271,
						"y": 217,
						"w": 15,
						"h": 18
					},
					"anchor": {
						"x": 0.5,
						"y": 0.5
					}
				},
				{
					"filename": "7/1/0/0",
					"rotated": false,
					"trimmed": false,
					"sourceSize": {
						"w": 15,
						"h": 18
					},
					"spriteSourceSize": {
						"x": 0,
						"y": 0,
						"w": 15,
						"h": 18
					},
					"frame": {
						"x": 271,
						"y": 217,
						"w": 15,
						"h": 18
					},
					"anchor": {
						"x": 0.46666667,
						"y": 0.5
					}
				},
				{
					"filename": "1/0/3/0",
					"rotated": false,
					"trimmed": false,
					"sourceSize": {
						"w": 22,
						"h": 22
					},
					"spriteSourceSize": {
						"x": 0,
						"y": 0,
						"w": 22,
						"h": 22
					},
					"frame": {
						"x": 246,
						"y": 230,
						"w": 22,
						"h": 22
					},
					"anchor": {
						"x": 0.5,
						"y": 0.5
					}
				},
				{
					"filename": "7/0/4/2",
					"rotated": false,
					"trimmed": false,
					"sourceSize": {
						"w": 16,
						"h": 19
					},
					"spriteSourceSize": {
						"x": 0,
						"y": 0,
						"w": 16,
						"h": 19
					},
					"frame": {
						"x": 270,
						"y": 237,
						"w": 16,
						"h": 19
					},
					"anchor": {
						"x": 0.5,
						"y": 0.5
					}
				},
				{
					"filename": "7/1/4/2",
					"rotated": false,
					"trimmed": false,
					"sourceSize": {
						"w": 16,
						"h": 19
					},
					"spriteSourceSize": {
						"x": 0,
						"y": 0,
						"w": 16,
						"h": 19
					},
					"frame": {
						"x": 270,
						"y": 237,
						"w": 16,
						"h": 19
					},
					"anchor": {
						"x": 0.5,
						"y": 0.7368421052631579
					}
				},
				{
					"filename": "4/1/2/1",
					"rotated": false,
					"trimmed": false,
					"sourceSize": {
						"w": 22,
						"h": 19
					},
					"spriteSourceSize": {
						"x": 0,
						"y": 0,
						"w": 22,
						"h": 19
					},
					"frame": {
						"x": 246,
						"y": 254,
						"w": 22,
						"h": 19
					},
					"anchor": {
						"x": 1,
						"y": 0.5263157894736842
					}
				},
				{
					"filename": "7/0/0/2",
					"rotated": false,
					"trimmed": false,
					"sourceSize": {
						"w": 15,
						"h": 18
					},
					"spriteSourceSize": {
						"x": 0,
						"y": 0,
						"w": 15,
						"h": 18
					},
					"frame": {
						"x": 270,
						"y": 258,
						"w": 15,
						"h": 18
					},
					"anchor": {
						"x": 0.5,
						"y": 0.5
					}
				},
				{
					"filename": "7/1/0/2",
					"rotated": false,
					"trimmed": false,
					"sourceSize": {
						"w": 15,
						"h": 18
					},
					"spriteSourceSize": {
						"x": 0,
						"y": 0,
						"w": 15,
						"h": 18
					},
					"frame": {
						"x": 270,
						"y": 258,
						"w": 15,
						"h": 18
					},
					"anchor": {
						"x": 0.4666666666666667,
						"y": 0.2777777777777778
					}
				},
				{
					"filename": "7/0/1/2",
					"rotated": false,
					"trimmed": false,
					"sourceSize": {
						"w": 22,
						"h": 19
					},
					"spriteSourceSize": {
						"x": 0,
						"y": 0,
						"w": 22,
						"h": 19
					},
					"frame": {
						"x": 246,
						"y": 275,
						"w": 22,
						"h": 19
					},
					"anchor": {
						"x": 0.5,
						"y": 0.5
					}
				},
				{
					"filename": "7/1/1/2",
					"rotated": false,
					"trimmed": false,
					"sourceSize": {
						"w": 22,
						"h": 19
					},
					"spriteSourceSize": {
						"x": 0,
						"y": 0,
						"w": 22,
						"h": 19
					},
					"frame": {
						"x": 246,
						"y": 275,
						"w": 22,
						"h": 19
					},
					"anchor": {
						"x": 0.77272727,
						"y": 0.21052632
					}
				},
				{
					"filename": "4/0/4/2",
					"rotated": false,
					"trimmed": false,
					"sourceSize": {
						"w": 14,
						"h": 22
					},
					"spriteSourceSize": {
						"x": 0,
						"y": 0,
						"w": 14,
						"h": 22
					},
					"frame": {
						"x": 270,
						"y": 278,
						"w": 14,
						"h": 22
					},
					"anchor": {
						"x": 0.5,
						"y": 0.5
					}
				},
				{
					"filename": "1/0/3/1",
					"rotated": false,
					"trimmed": false,
					"sourceSize": {
						"w": 22,
						"h": 18
					},
					"spriteSourceSize": {
						"x": 0,
						"y": 0,
						"w": 22,
						"h": 18
					},
					"frame": {
						"x": 246,
						"y": 296,
						"w": 22,
						"h": 18
					},
					"anchor": {
						"x": 0.5,
						"y": 0.5
					}
				},
				{
					"filename": "1/0/1/1",
					"rotated": false,
					"trimmed": false,
					"sourceSize": {
						"w": 21,
						"h": 22
					},
					"spriteSourceSize": {
						"x": 0,
						"y": 0,
						"w": 21,
						"h": 22
					},
					"frame": {
						"x": 246,
						"y": 316,
						"w": 21,
						"h": 22
					},
					"anchor": {
						"x": 0.5,
						"y": 0.5
					}
				},
				{
					"filename": "1/0/0/1",
					"rotated": false,
					"trimmed": false,
					"sourceSize": {
						"w": 17,
						"h": 22
					},
					"spriteSourceSize": {
						"x": 0,
						"y": 0,
						"w": 17,
						"h": 22
					},
					"frame": {
						"x": 269,
						"y": 316,
						"w": 17,
						"h": 22
					},
					"anchor": {
						"x": 0.5,
						"y": 0.5
					}
				},
				{
					"filename": "4/1/3/1",
					"rotated": false,
					"trimmed": false,
					"sourceSize": {
						"w": 21,
						"h": 21
					},
					"spriteSourceSize": {
						"x": 0,
						"y": 0,
						"w": 21,
						"h": 21
					},
					"frame": {
						"x": 246,
						"y": 340,
						"w": 21,
						"h": 21
					},
					"anchor": {
						"x": 1,
						"y": 1
					}
				},
				{
					"filename": "1/0/4/0",
					"rotated": false,
					"trimmed": false,
					"sourceSize": {
						"w": 17,
						"h": 22
					},
					"spriteSourceSize": {
						"x": 0,
						"y": 0,
						"w": 17,
						"h": 22
					},
					"frame": {
						"x": 269,
						"y": 340,
						"w": 17,
						"h": 22
					},
					"anchor": {
						"x": 0.5,
						"y": 0.5
					}
				},
				{
					"filename": "4/1/3/2",
					"rotated": false,
					"trimmed": false,
					"sourceSize": {
						"w": 21,
						"h": 21
					},
					"spriteSourceSize": {
						"x": 0,
						"y": 0,
						"w": 21,
						"h": 21
					},
					"frame": {
						"x": 246,
						"y": 363,
						"w": 21,
						"h": 21
					},
					"anchor": {
						"x": 0.6190476190476191,
						"y": 0.6666666666666666
					}
				},
				{
					"filename": "4/0/0/2",
					"rotated": false,
					"trimmed": false,
					"sourceSize": {
						"w": 17,
						"h": 22
					},
					"spriteSourceSize": {
						"x": 0,
						"y": 0,
						"w": 17,
						"h": 22
					},
					"frame": {
						"x": 269,
						"y": 364,
						"w": 17,
						"h": 22
					},
					"anchor": {
						"x": 0.5,
						"y": 0.5
					}
				},
				{
					"filename": "1/0/2/0",
					"rotated": false,
					"trimmed": false,
					"sourceSize": {
						"w": 21,
						"h": 20
					},
					"spriteSourceSize": {
						"x": 0,
						"y": 0,
						"w": 21,
						"h": 20
					},
					"frame": {
						"x": 246,
						"y": 386,
						"w": 21,
						"h": 20
					},
					"anchor": {
						"x": 0.5,
						"y": 0.5
					}
				},
				{
					"filename": "1/0/0/2",
					"rotated": false,
					"trimmed": false,
					"sourceSize": {
						"w": 17,
						"h": 21
					},
					"spriteSourceSize": {
						"x": 0,
						"y": 0,
						"w": 17,
						"h": 21
					},
					"frame": {
						"x": 269,
						"y": 388,
						"w": 17,
						"h": 21
					},
					"anchor": {
						"x": 0.5,
						"y": 0.5
					}
				},
				{
					"filename": "4/0/2/0",
					"rotated": false,
					"trimmed": false,
					"sourceSize": {
						"w": 21,
						"h": 20
					},
					"spriteSourceSize": {
						"x": 0,
						"y": 0,
						"w": 21,
						"h": 20
					},
					"frame": {
						"x": 246,
						"y": 408,
						"w": 21,
						"h": 20
					},
					"anchor": {
						"x": 0.5,
						"y": 0.5
					}
				},
				{
					"filename": "1/1/0/1",
					"rotated": false,
					"trimmed": false,
					"sourceSize": {
						"w": 17,
						"h": 21
					},
					"spriteSourceSize": {
						"x": 0,
						"y": 0,
						"w": 17,
						"h": 21
					},
					"frame": {
						"x": 269,
						"y": 411,
						"w": 17,
						"h": 21
					},
					"anchor": {
						"x": 0.5,
						"y": 0.5
					}
				},
				{
					"filename": "1/0/2/2",
					"rotated": false,
					"trimmed": false,
					"sourceSize": {
						"w": 21,
						"h": 18
					},
					"spriteSourceSize": {
						"x": 0,
						"y": 0,
						"w": 21,
						"h": 18
					},
					"frame": {
						"x": 246,
						"y": 430,
						"w": 21,
						"h": 18
					},
					"anchor": {
						"x": 0.5,
						"y": 0.5
					}
				},
				{
					"filename": "4/1/1/2",
					"rotated": false,
					"trimmed": false,
					"sourceSize": {
						"w": 17,
						"h": 21
					},
					"spriteSourceSize": {
						"x": 0,
						"y": 0,
						"w": 17,
						"h": 21
					},
					"frame": {
						"x": 269,
						"y": 434,
						"w": 17,
						"h": 21
					},
					"anchor": {
						"x": 0.7647058823529411,
						"y": 0.2857142857142857
					}
				},
				{
					"filename": "4/0/1/2",
					"rotated": false,
					"trimmed": false,
					"sourceSize": {
						"w": 20,
						"h": 21
					},
					"spriteSourceSize": {
						"x": 0,
						"y": 0,
						"w": 20,
						"h": 21
					},
					"frame": {
						"x": 246,
						"y": 450,
						"w": 20,
						"h": 21
					},
					"anchor": {
						"x": 0.5,
						"y": 0.5
					}
				},
				{
					"filename": "4/1/0/0",
					"rotated": false,
					"trimmed": false,
					"sourceSize": {
						"w": 18,
						"h": 22
					},
					"spriteSourceSize": {
						"x": 0,
						"y": 0,
						"w": 18,
						"h": 22
					},
					"frame": {
						"x": 268,
						"y": 457,
						"w": 18,
						"h": 22
					},
					"anchor": {
						"x": 0.5,
						"y": 0.5
					}
				},
				{
					"filename": "4/0/2/1",
					"rotated": false,
					"trimmed": false,
					"sourceSize": {
						"w": 20,
						"h": 21
					},
					"spriteSourceSize": {
						"x": 0,
						"y": 0,
						"w": 20,
						"h": 21
					},
					"frame": {
						"x": 246,
						"y": 473,
						"w": 20,
						"h": 21
					},
					"anchor": {
						"x": 0.5,
						"y": 0.5
					}
				},
				{
					"filename": "1/1/1/1",
					"rotated": false,
					"trimmed": false,
					"sourceSize": {
						"w": 18,
						"h": 21
					},
					"spriteSourceSize": {
						"x": 0,
						"y": 0,
						"w": 18,
						"h": 21
					},
					"frame": {
						"x": 268,
						"y": 481,
						"w": 18,
						"h": 21
					},
					"anchor": {
						"x": 0.5,
						"y": 0.5
					}
				},
				{
					"filename": "4/1/1/1",
					"rotated": false,
					"trimmed": false,
					"sourceSize": {
						"w": 20,
						"h": 21
					},
					"spriteSourceSize": {
						"x": 0,
						"y": 0,
						"w": 20,
						"h": 21
					},
					"frame": {
						"x": 246,
						"y": 496,
						"w": 20,
						"h": 21
					},
					"anchor": {
						"x": 1,
						"y": 0
					}
				},
				{
					"filename": "4/0/0/0",
					"rotated": false,
					"trimmed": false,
					"sourceSize": {
						"w": 18,
						"h": 21
					},
					"spriteSourceSize": {
						"x": 0,
						"y": 0,
						"w": 18,
						"h": 21
					},
					"frame": {
						"x": 268,
						"y": 504,
						"w": 18,
						"h": 21
					},
					"anchor": {
						"x": 0.5,
						"y": 0.5
					}
				},
				{
					"filename": "1/0/3/2",
					"rotated": false,
					"trimmed": false,
					"sourceSize": {
						"w": 20,
						"h": 20
					},
					"spriteSourceSize": {
						"x": 0,
						"y": 0,
						"w": 20,
						"h": 20
					},
					"frame": {
						"x": 246,
						"y": 519,
						"w": 20,
						"h": 20
					},
					"anchor": {
						"x": 0.5,
						"y": 0.5
					}
				},
				{
					"filename": "4/1/0/1",
					"rotated": false,
					"trimmed": false,
					"sourceSize": {
						"w": 18,
						"h": 21
					},
					"spriteSourceSize": {
						"x": 0,
						"y": 0,
						"w": 18,
						"h": 21
					},
					"frame": {
						"x": 268,
						"y": 527,
						"w": 18,
						"h": 21
					},
					"anchor": {
						"x": 0.5,
						"y": 0
					}
				},
				{
					"filename": "4/0/2/2",
					"rotated": false,
					"trimmed": false,
					"sourceSize": {
						"w": 20,
						"h": 20
					},
					"spriteSourceSize": {
						"x": 0,
						"y": 0,
						"w": 20,
						"h": 20
					},
					"frame": {
						"x": 246,
						"y": 541,
						"w": 20,
						"h": 20
					},
					"anchor": {
						"x": 0.5,
						"y": 0.5
					}
				},
				{
					"filename": "1/1/1/0",
					"rotated": false,
					"trimmed": false,
					"sourceSize": {
						"w": 18,
						"h": 20
					},
					"spriteSourceSize": {
						"x": 0,
						"y": 0,
						"w": 18,
						"h": 20
					},
					"frame": {
						"x": 268,
						"y": 550,
						"w": 18,
						"h": 20
					},
					"anchor": {
						"x": 0.5,
						"y": 0.5
					}
				},
				{
					"filename": "4/0/3/2",
					"rotated": false,
					"trimmed": false,
					"sourceSize": {
						"w": 20,
						"h": 20
					},
					"spriteSourceSize": {
						"x": 0,
						"y": 0,
						"w": 20,
						"h": 20
					},
					"frame": {
						"x": 246,
						"y": 563,
						"w": 20,
						"h": 20
					},
					"anchor": {
						"x": 0.5,
						"y": 0.5
					}
				},
				{
					"filename": "4/0/3/0",
					"rotated": false,
					"trimmed": false,
					"sourceSize": {
						"w": 18,
						"h": 20
					},
					"spriteSourceSize": {
						"x": 0,
						"y": 0,
						"w": 18,
						"h": 20
					},
					"frame": {
						"x": 268,
						"y": 572,
						"w": 18,
						"h": 20
					},
					"anchor": {
						"x": 0.5,
						"y": 0.5
					}
				},
				{
					"filename": "7/0/3/0",
					"rotated": false,
					"trimmed": false,
					"sourceSize": {
						"w": 20,
						"h": 20
					},
					"spriteSourceSize": {
						"x": 0,
						"y": 0,
						"w": 20,
						"h": 20
					},
					"frame": {
						"x": 246,
						"y": 585,
						"w": 20,
						"h": 20
					},
					"anchor": {
						"x": 0.5,
						"y": 0.5
					}
				},
				{
					"filename": "7/1/3/0",
					"rotated": false,
					"trimmed": false,
					"sourceSize": {
						"w": 20,
						"h": 20
					},
					"spriteSourceSize": {
						"x": 0,
						"y": 0,
						"w": 20,
						"h": 20
					},
					"frame": {
						"x": 246,
						"y": 585,
						"w": 20,
						"h": 20
					},
					"anchor": {
						"x": 0.5,
						"y": 0.5
					}
				},
				{
					"filename": "4/1/0/2",
					"rotated": false,
					"trimmed": false,
					"sourceSize": {
						"w": 18,
						"h": 20
					},
					"spriteSourceSize": {
						"x": 0,
						"y": 0,
						"w": 18,
						"h": 20
					},
					"frame": {
						"x": 268,
						"y": 594,
						"w": 18,
						"h": 20
					},
					"anchor": {
						"x": 0.55555556,
						"y": 0.3
					}
				},
				{
					"filename": "7/0/3/1",
					"rotated": false,
					"trimmed": false,
					"sourceSize": {
						"w": 20,
						"h": 20
					},
					"spriteSourceSize": {
						"x": 0,
						"y": 0,
						"w": 20,
						"h": 20
					},
					"frame": {
						"x": 246,
						"y": 607,
						"w": 20,
						"h": 20
					},
					"anchor": {
						"x": 0.5,
						"y": 0.5
					}
				},
				{
					"filename": "7/1/3/1",
					"rotated": false,
					"trimmed": false,
					"sourceSize": {
						"w": 20,
						"h": 20
					},
					"spriteSourceSize": {
						"x": 0,
						"y": 0,
						"w": 20,
						"h": 20
					},
					"frame": {
						"x": 246,
						"y": 607,
						"w": 20,
						"h": 20
					},
					"anchor": {
						"x": 1,
						"y": 1
					}
				},
				{
					"filename": "7/0/1/0",
					"rotated": false,
					"trimmed": false,
					"sourceSize": {
						"w": 18,
						"h": 20
					},
					"spriteSourceSize": {
						"x": 0,
						"y": 0,
						"w": 18,
						"h": 20
					},
					"frame": {
						"x": 268,
						"y": 616,
						"w": 18,
						"h": 20
					},
					"anchor": {
						"x": 0.5,
						"y": 0.5
					}
				},
				{
					"filename": "7/1/1/0",
					"rotated": false,
					"trimmed": false,
					"sourceSize": {
						"w": 18,
						"h": 20
					},
					"spriteSourceSize": {
						"x": 0,
						"y": 0,
						"w": 18,
						"h": 20
					},
					"frame": {
						"x": 268,
						"y": 616,
						"w": 18,
						"h": 20
					},
					"anchor": {
						"x": 0.5,
						"y": 0.5
					}
				},
				{
					"filename": "1/0/1/2",
					"rotated": false,
					"trimmed": false,
					"sourceSize": {
						"w": 20,
						"h": 19
					},
					"spriteSourceSize": {
						"x": 0,
						"y": 0,
						"w": 20,
						"h": 19
					},
					"frame": {
						"x": 246,
						"y": 629,
						"w": 20,
						"h": 19
					},
					"anchor": {
						"x": 0.5,
						"y": 0.5
					}
				},
				{
					"filename": "1/1/3/0",
					"rotated": false,
					"trimmed": false,
					"sourceSize": {
						"w": 18,
						"h": 19
					},
					"spriteSourceSize": {
						"x": 0,
						"y": 0,
						"w": 18,
						"h": 19
					},
					"frame": {
						"x": 268,
						"y": 638,
						"w": 18,
						"h": 19
					},
					"anchor": {
						"x": 0.5,
						"y": 0.5
					}
				},
				{
					"filename": "4/1/2/2",
					"rotated": false,
					"trimmed": false,
					"sourceSize": {
						"w": 20,
						"h": 19
					},
					"spriteSourceSize": {
						"x": 0,
						"y": 0,
						"w": 20,
						"h": 19
					},
					"frame": {
						"x": 246,
						"y": 650,
						"w": 20,
						"h": 19
					},
					"anchor": {
						"x": 0.7,
						"y": 0.5263157894736842
					}
				},
				{
					"filename": "1/1/3/1",
					"rotated": false,
					"trimmed": false,
					"sourceSize": {
						"w": 18,
						"h": 19
					},
					"spriteSourceSize": {
						"x": 0,
						"y": 0,
						"w": 18,
						"h": 19
					},
					"frame": {
						"x": 268,
						"y": 659,
						"w": 18,
						"h": 19
					},
					"anchor": {
						"x": 0.5,
						"y": 0.5
					}
				},
				{
					"filename": "7/0/1/1",
					"rotated": false,
					"trimmed": false,
					"sourceSize": {
						"w": 20,
						"h": 19
					},
					"spriteSourceSize": {
						"x": 0,
						"y": 0,
						"w": 20,
						"h": 19
					},
					"frame": {
						"x": 246,
						"y": 671,
						"w": 20,
						"h": 19
					},
					"anchor": {
						"x": 0.5,
						"y": 0.5
					}
				},
				{
					"filename": "7/1/1/1",
					"rotated": false,
					"trimmed": false,
					"sourceSize": {
						"w": 20,
						"h": 19
					},
					"spriteSourceSize": {
						"x": 0,
						"y": 0,
						"w": 20,
						"h": 19
					},
					"frame": {
						"x": 246,
						"y": 671,
						"w": 20,
						"h": 19
					},
					"anchor": {
						"x": 1,
						"y": 0
					}
				},
				{
					"filename": "4/0/1/0",
					"rotated": false,
					"trimmed": false,
					"sourceSize": {
						"w": 18,
						"h": 19
					},
					"spriteSourceSize": {
						"x": 0,
						"y": 0,
						"w": 18,
						"h": 19
					},
					"frame": {
						"x": 268,
						"y": 680,
						"w": 18,
						"h": 19
					},
					"anchor": {
						"x": 0.5,
						"y": 0.5
					}
				},
				{
					"filename": "1/0/0/0",
					"rotated": false,
					"trimmed": false,
					"sourceSize": {
						"w": 19,
						"h": 21
					},
					"spriteSourceSize": {
						"x": 0,
						"y": 0,
						"w": 19,
						"h": 21
					},
					"frame": {
						"x": 246,
						"y": 692,
						"w": 19,
						"h": 21
					},
					"anchor": {
						"x": 0.5,
						"y": 0.5
					}
				},
				{
					"filename": "1/1/2/1",
					"rotated": false,
					"trimmed": false,
					"sourceSize": {
						"w": 19,
						"h": 21
					},
					"spriteSourceSize": {
						"x": 0,
						"y": 0,
						"w": 19,
						"h": 21
					},
					"frame": {
						"x": 267,
						"y": 701,
						"w": 19,
						"h": 21
					},
					"anchor": {
						"x": 0.5,
						"y": 0.5
					}
				},
				{
					"filename": "4/0/0/1",
					"rotated": false,
					"trimmed": false,
					"sourceSize": {
						"w": 19,
						"h": 21
					},
					"spriteSourceSize": {
						"x": 0,
						"y": 0,
						"w": 19,
						"h": 21
					},
					"frame": {
						"x": 246,
						"y": 715,
						"w": 19,
						"h": 21
					},
					"anchor": {
						"x": 0.5,
						"y": 0.5
					}
				},
				{
					"filename": "4/0/1/1",
					"rotated": false,
					"trimmed": false,
					"sourceSize": {
						"w": 19,
						"h": 21
					},
					"spriteSourceSize": {
						"x": 0,
						"y": 0,
						"w": 19,
						"h": 21
					},
					"frame": {
						"x": 267,
						"y": 724,
						"w": 19,
						"h": 21
					},
					"anchor": {
						"x": 0.5,
						"y": 0.5
					}
				},
				{
					"filename": "4/1/1/0",
					"rotated": false,
					"trimmed": false,
					"sourceSize": {
						"w": 19,
						"h": 21
					},
					"spriteSourceSize": {
						"x": 0,
						"y": 0,
						"w": 19,
						"h": 21
					},
					"frame": {
						"x": 246,
						"y": 738,
						"w": 19,
						"h": 21
					},
					"anchor": {
						"x": 0.5,
						"y": 0.5
					}
				},
				{
					"filename": "4/1/4/1",
					"rotated": false,
					"trimmed": false,
					"sourceSize": {
						"w": 19,
						"h": 21
					},
					"spriteSourceSize": {
						"x": 0,
						"y": 0,
						"w": 19,
						"h": 21
					},
					"frame": {
						"x": 267,
						"y": 747,
						"w": 19,
						"h": 21
					},
					"anchor": {
						"x": 0.5263157894736842,
						"y": 1
					}
				},
				{
					"filename": "4/1/4/2",
					"rotated": false,
					"trimmed": false,
					"sourceSize": {
						"w": 19,
						"h": 21
					},
					"spriteSourceSize": {
						"x": 0,
						"y": 0,
						"w": 19,
						"h": 21
					},
					"frame": {
						"x": 246,
						"y": 761,
						"w": 19,
						"h": 21
					},
					"anchor": {
						"x": 0.47368421052631576,
						"y": 0.6666666666666666
					}
				},
				{
					"filename": "1/1/2/0",
					"rotated": false,
					"trimmed": false,
					"sourceSize": {
						"w": 19,
						"h": 20
					},
					"spriteSourceSize": {
						"x": 0,
						"y": 0,
						"w": 19,
						"h": 20
					},
					"frame": {
						"x": 267,
						"y": 770,
						"w": 19,
						"h": 20
					},
					"anchor": {
						"x": 0.5,
						"y": 0.5
					}
				},
				{
					"filename": "4/0/3/1",
					"rotated": false,
					"trimmed": false,
					"sourceSize": {
						"w": 19,
						"h": 20
					},
					"spriteSourceSize": {
						"x": 0,
						"y": 0,
						"w": 19,
						"h": 20
					},
					"frame": {
						"x": 246,
						"y": 784,
						"w": 19,
						"h": 20
					},
					"anchor": {
						"x": 0.5,
						"y": 0.5
					}
				},
				{
					"filename": "4/1/2/0",
					"rotated": false,
					"trimmed": false,
					"sourceSize": {
						"w": 19,
						"h": 20
					},
					"spriteSourceSize": {
						"x": 0,
						"y": 0,
						"w": 19,
						"h": 20
					},
					"frame": {
						"x": 267,
						"y": 792,
						"w": 19,
						"h": 20
					},
					"anchor": {
						"x": 0.5,
						"y": 0.5
					}
				},
				{
					"filename": "4/1/4/0",
					"rotated": false,
					"trimmed": false,
					"sourceSize": {
						"w": 19,
						"h": 20
					},
					"spriteSourceSize": {
						"x": 0,
						"y": 0,
						"w": 19,
						"h": 20
					},
					"frame": {
						"x": 246,
						"y": 806,
						"w": 19,
						"h": 20
					},
					"anchor": {
						"x": 0.5,
						"y": 0.5
					}
				},
				{
					"filename": "7/0/3/2",
					"rotated": false,
					"trimmed": false,
					"sourceSize": {
						"w": 19,
						"h": 19
					},
					"spriteSourceSize": {
						"x": 0,
						"y": 0,
						"w": 19,
						"h": 19
					},
					"frame": {
						"x": 267,
						"y": 814,
						"w": 19,
						"h": 19
					},
					"anchor": {
						"x": 0.5,
						"y": 0.5
					}
				},
				{
					"filename": "7/1/3/2",
					"rotated": false,
					"trimmed": false,
					"sourceSize": {
						"w": 19,
						"h": 19
					},
					"spriteSourceSize": {
						"x": 0,
						"y": 0,
						"w": 19,
						"h": 19
					},
					"frame": {
						"x": 267,
						"y": 814,
						"w": 19,
						"h": 19
					},
					"anchor": {
						"x": 0.7368421052631579,
						"y": 0.7368421052631579
					}
				},
				{
					"filename": "1/0/4/2",
					"rotated": false,
					"trimmed": false,
					"sourceSize": {
						"w": 17,
						"h": 20
					},
					"spriteSourceSize": {
						"x": 0,
						"y": 0,
						"w": 17,
						"h": 20
					},
					"frame": {
						"x": 246,
						"y": 828,
						"w": 17,
						"h": 20
					},
					"anchor": {
						"x": 0.5,
						"y": 0.5
					}
				},
				{
					"filename": "1/1/0/0",
					"rotated": false,
					"trimmed": false,
					"sourceSize": {
						"w": 17,
						"h": 20
					},
					"spriteSourceSize": {
						"x": 0,
						"y": 0,
						"w": 17,
						"h": 20
					},
					"frame": {
						"x": 265,
						"y": 835,
						"w": 17,
						"h": 20
					},
					"anchor": {
						"x": 0.5,
						"y": 0.5
					}
				},
				{
					"filename": "4/1/3/0",
					"rotated": false,
					"trimmed": false,
					"sourceSize": {
						"w": 17,
						"h": 20
					},
					"spriteSourceSize": {
						"x": 0,
						"y": 0,
						"w": 17,
						"h": 20
					},
					"frame": {
						"x": 246,
						"y": 850,
						"w": 17,
						"h": 20
					},
					"anchor": {
						"x": 0.5,
						"y": 0.5
					}
				},
				{
					"filename": "1/1/4/0",
					"rotated": false,
					"trimmed": false,
					"sourceSize": {
						"w": 17,
						"h": 18
					},
					"spriteSourceSize": {
						"x": 0,
						"y": 0,
						"w": 17,
						"h": 18
					},
					"frame": {
						"x": 265,
						"y": 857,
						"w": 17,
						"h": 18
					},
					"anchor": {
						"x": 0.5,
						"y": 0.5
					}
				},
				{
					"filename": "1/1/4/1",
					"rotated": false,
					"trimmed": false,
					"sourceSize": {
						"w": 17,
						"h": 18
					},
					"spriteSourceSize": {
						"x": 0,
						"y": 0,
						"w": 17,
						"h": 18
					},
					"frame": {
						"x": 246,
						"y": 872,
						"w": 17,
						"h": 18
					},
					"anchor": {
						"x": 0.5,
						"y": 0.5
					}
				},
				{
					"filename": "7/0/0/1",
					"rotated": false,
					"trimmed": false,
					"sourceSize": {
						"w": 17,
						"h": 18
					},
					"spriteSourceSize": {
						"x": 0,
						"y": 0,
						"w": 17,
						"h": 18
					},
					"frame": {
						"x": 265,
						"y": 877,
						"w": 17,
						"h": 18
					},
					"anchor": {
						"x": 0.5,
						"y": 0.5
					}
				},
				{
					"filename": "7/1/0/1",
					"rotated": false,
					"trimmed": false,
					"sourceSize": {
						"w": 17,
						"h": 18
					},
					"spriteSourceSize": {
						"x": 0,
						"y": 0,
						"w": 17,
						"h": 18
					},
					"frame": {
						"x": 265,
						"y": 877,
						"w": 17,
						"h": 18
					},
					"anchor": {
						"x": 0.47058824,
						"y": 0
					}
				},
				{
					"filename": "1/0/4/1",
					"rotated": false,
					"trimmed": false,
					"sourceSize": {
						"w": 17,
						"h": 16
					},
					"spriteSourceSize": {
						"x": 0,
						"y": 0,
						"w": 17,
						"h": 16
					},
					"frame": {
						"x": 246,
						"y": 892,
						"w": 17,
						"h": 16
					},
					"anchor": {
						"x": 0.5,
						"y": 0.5
					}
				}
			]
		}
	],
	"meta": {
		"app": "https://www.codeandweb.com/texturepacker",
		"version": "3.0",
		"smartupdate": "$TexturePacker:SmartUpdate:7ea91cfa3c517fa9ce3875857d5ca71a:f7b798fa00e38ab7ea73bfa9b60201e9:46c22ca313450a7c238cae1bf5ea1171$"
	}
}
